[
  {
    "id": "dafe77fb-33d4-4aeb-8411-28040397a94a",
    "status": "submitted",
    "job_posting": "fac3dceb-28b8-472e-8868-7dbdb41a7f33",
    "first_name": "Alexandra",
    "last_name": "Martinez",
    "email": "alexandra.martinez@example.com",
    "phone": "+1-555-0245",
    "resume": "03b3a7e7-a338-4836-822f-9ec0e0bde30b",
    "cover_letter": "966975fb-23ee-4760-8cb8-5717d0bf0282",
    "linkedin_url": "https://linkedin.com/in/alexandra-martinez",
    "portfolio_url": null,
    "years_of_experience": 5,
    "current_company": "TechStartup Inc",
    "expected_salary": "$120,000 - $140,000",
    "available_start_date": "2025-04-01",
    "how_did_you_hear": "linkedin",
    "additional_info": "I'm passionate about building scalable systems and have experience leading development teams.",
    "recruiter_notes": null,
    "sort": null,
    "date_created": "2025-12-11T02:15:02.999Z",
    "date_updated": null
  },
  {
    "id": "6e45c287-5415-4c00-92ec-b8c90060b127",
    "status": "under_review",
    "job_posting": "a52f4b6a-8ba0-488f-b7a7-0bfa4e2e1265",
    "first_name": "David",
    "last_name": "Thompson",
    "email": "david.thompson@example.com",
    "phone": "+1-555-0289",
    "resume": "23615faa-e596-498f-b549-73f721437456",
    "cover_letter": null,
    "linkedin_url": "https://linkedin.com/in/davidthompson",
    "portfolio_url": "https://davidthompson.dev",
    "years_of_experience": 3,
    "current_company": "Digital Agency Co",
    "expected_salary": null,
    "available_start_date": "2025-03-15",
    "how_did_you_hear": "company_website",
    "additional_info": null,
    "recruiter_notes": "Strong technical background. Scheduled for phone screen next week.",
    "sort": null,
    "date_created": "2025-12-11T02:15:03.006Z",
    "date_updated": null
  }
]